[
  [
    {
      "x": 3.5,
      "sm": "cherry",
      "a": 5
    },
    "#\n3\n\n\nF3",
    {
      "x": 8.5
    },
    "*\n8\n\n\nF8"
  ],
  [
    {
      "y": -0.875,
      "x": 2.5
    },
    "@\n2\n\n\nF2",
    {
      "x": 1
    },
    "$\n4\n\n\nF4",
    {
      "x": 6.5
    },
    "&\n7\n\n\nF7",
    {
      "x": 1
    },
    "(\n9\n\n\nF9"
  ],
  [
    {
      "y": -0.875,
      "x": 5.5
    },
    "%\n5\n\n\nF5",
    {
      "x": 4.5
    },
    "^\n6\n\n\nF6"
  ],
  [
    {
      "y": -0.875,
      "x": 0.5
    },
    "~\n`",
    "!\n1\n\n\nF1",
    {
      "x": 12.5
    },
    ")\n0\n\n\nF10",
    "_\n-\n\n\nF11",
    "+\n=\n\n\nF12",
    {
      "a": 7,
      "w": 1.5
    },
    "←\n\n\n\nDel"
  ],
  [
    {
      "y": -0.375,
      "x": 3.5
    },
    "E",
    {
      "x": 8.5
    },
    "I\n\n\n\nPgUp"
  ],
  [
    {
      "y": -0.875,
      "x": 2.5
    },
    "W",
    {
      "x": 1
    },
    "R",
    {
      "x": 6.5
    },
    "U\n\n\n\nPgDn",
    {
      "x": 1
    },
    "O\n\n\n\nEnd"
  ],
  [
    {
      "y": -0.875,
      "x": 5.5
    },
    "T",
    {
      "x": 4.5
    },
    "Y\n\n\n\nHome"
  ],
  [
    {
      "y": -0.875,
      "w": 1.5
    },
    "Tab",
    "Q",
    {
      "x": 12.5
    },
    "P",
    {
      "a": 5
    },
    "{\n[\n\n\nPrtScr",
    "}\n]\n\n\nScrLk",
    {
      "w": 1.5
    },
    "|\n\\\n\n\nPause"
  ],
  [
    {
      "y": -0.375,
      "x": 3.5,
      "a": 7
    },
    "D",
    {
      "x": 8.5
    },
    "K\n\n\n\n↑"
  ],
  [
    {
      "y": -0.875,
      "x": 2.5
    },
    "S",
    {
      "x": 1,
      "n": true
    },
    "F",
    {
      "x": 6.5,
      "n": true
    },
    "J\n\n\n\n↓",
    {
      "x": 1
    },
    "L\n\n\n\n→"
  ],
  [
    {
      "y": -0.875,
      "x": 5.5
    },
    "G",
    {
      "x": 4.5
    },
    "H\n\n\n\n←"
  ],
  [
    {
      "y": -0.875,
      "w": 1.5
    },
    "Esc",
    "A",
    {
      "x": 12.5,
      "a": 5
    },
    ":\n;",
    "\"\n'",
    {
      "a": 7,
      "w": 1.5
    },
    "Enter"
  ],
  [
    {
      "y": -0.375,
      "x": 3.5
    },
    "C",
    {
      "x": 8.5,
      "a": 5
    },
    "<\n,"
  ],
  [
    {
      "y": -0.875,
      "x": 2.5,
      "a": 7
    },
    "X",
    {
      "x": 1
    },
    "V",
    {
      "x": 6.5
    },
    "M",
    {
      "x": 1,
      "a": 5
    },
    ">\n."
  ],
  [
    {
      "y": -0.875,
      "x": 5.5,
      "a": 7
    },
    "B",
    {
      "x": 4.5
    },
    "N"
  ],
  [
    {
      "y": -0.875,
      "w": 1.5
    },
    "Shfit",
    "Z",
    {
      "x": 12.5,
      "a": 5
    },
    "?\n/",
    {
      "sm": ""
    },
    "|\n\\",
    {
      "sm": "cherry",
      "a": 7,
      "w": 1.5
    },
    "Shift\n\n\n\nCtrl"
  ],
  [
    {
      "y": -0.25,
      "x": 2.5
    },
    "Alt"
  ],
  [
    {
      "y": -0.75,
      "w": 1.5
    },
    "Ctrl",
    "Super"
  ],
  [
    {
      "r": 20,
      "rx": 5,
      "ry": 4.48,
      "y": -0.1800000000000006,
      "x": 0.5,
      "w": 1.5
    },
    ""
  ],
  [
    {
      "r": 30,
      "rx": 6.9,
      "ry": 4.85,
      "y": 0.10000000000000053,
      "x": 0.2999999999999998,
      "w": 1.5
    },
    ""
  ],
  [
    {
      "r": -30,
      "rx": 9.1,
      "y": 0.8500000000000005,
      "x": -0.5199999999999996,
      "sb": "cherry",
      "w": 1.5
    },
    ""
  ],
  [
    {
      "r": -20,
      "rx": 11,
      "ry": 4.48,
      "y": 0.3199999999999994,
      "x": -0.5999999999999996,
      "w": 1.5
    },
    ""
  ]
]